blackboxscan/__init__.py
blackboxscan/preprocess.py
blackboxscan/scanner.py
blackboxscan-0.1.1.dist-info/LICENSE
blackboxscan-0.1.1.dist-info/METADATA
blackboxscan-0.1.1.dist-info/WHEEL
blackboxscan-0.1.1.dist-info/entry_points.txt
blackboxscan-0.1.1.dist-info/top_level.txt
blackboxscan-0.1.1.dist-info/RECORD
