Metadata-Version: 2.1
Name: blackboxscan
Version: 0.1.1
Summary: A library to easily analyse the outputs of HuggingFace LLMs
Home-page: https://github.com/khyatikhandelwal/blackboxscan
Author: Khyati Khandelwal
Author-email: connect@khyatikhandelwal.com
Classifier: Programming Language :: Python :: 3
Classifier: License :: OSI Approved :: MIT License
Classifier: Operating System :: OS Independent
Requires-Python: >=3.6
License-File: LICENSE
